adif2xml/__init__.py
adif2xml/__main__.py
adif2xml-1.0.1.dist-info/LICENSE
adif2xml-1.0.1.dist-info/METADATA
adif2xml-1.0.1.dist-info/WHEEL
adif2xml-1.0.1.dist-info/entry_points.txt
adif2xml-1.0.1.dist-info/top_level.txt
adif2xml-1.0.1.dist-info/RECORD
